fantasy_rankings_scraper/__init__.py
fantasy_rankings_scraper/abstract_api_scraper.py
fantasy_rankings_scraper/abstract_html_scraper.py
fantasy_rankings_scraper/abstract_scraper.py
fantasy_rankings_scraper/cbssports.py
fantasy_rankings_scraper/fantasyfootballcalculator.py
fantasy_rankings_scraper/fantasypros.py
fantasy_rankings_scraper/format.py
fantasy_rankings_scraper/rotoballer.py
fantasy_rankings_scraper-0.0.4.dist-info/METADATA
fantasy_rankings_scraper-0.0.4.dist-info/WHEEL
fantasy_rankings_scraper-0.0.4.dist-info/licenses/LICENSE
fantasy_rankings_scraper-0.0.4.dist-info/RECORD
