Metadata-Version: 2.1
Name: fantasy-rankings-scraper
Version: 0.0.4
Summary: A Python package for scraping fantasy football players rankings across multiple sites.
Project-URL: Homepage, https://github.com/n-roth12/fantasy-rankings-scraper
Author: Nolan Roth
License-File: LICENSE
Classifier: License :: OSI Approved :: MIT License
Classifier: Operating System :: OS Independent
Classifier: Programming Language :: Python :: 3
Requires-Python: >=3.7
Requires-Dist: bs4
Requires-Dist: requests
